behold/__init__.py
behold/behold.py
behold/libs/__init__.py
behold/libs/athena.py
behold/libs/athena_query_strings.py
behold/libs/csv_parser.py
behold/libs/metadata.py
behold/libs/policy_generator.py
behold/libs/s3.py
behold/libs/utils.py
beholdiam-1.0.6.dist-info/LICENSE
beholdiam-1.0.6.dist-info/METADATA
beholdiam-1.0.6.dist-info/WHEEL
beholdiam-1.0.6.dist-info/entry_points.txt
beholdiam-1.0.6.dist-info/top_level.txt
beholdiam-1.0.6.dist-info/RECORD
