Metadata-Version: 2.1
Name: beholdiam
Version: 1.0.6
Summary: Behold uses Athena and CloudTrail to audit your IAM resources and generate policy recommendations.
Home-page: https://github.com/kwkeefer/behold
Author: Kyle Keefer
Author-email: kyle.keefer@protonmail.com
License: MIT
Platform: UNKNOWN
Requires-Dist: boto3
Requires-Dist: PyYAML
Requires-Dist: requests
